aedev/project_tpls/__init__.py
aedev/project_tpls/templates/de_otf_LICENSE.md
aedev/project_tpls/templates/de_otf_SECURITY.md
aedev/project_tpls/templates/de_otf_de_tpl_.gitignore
aedev/project_tpls/templates/de_otf_de_tpl_.gitlab-ci.yml
aedev/project_tpls/templates/de_otf_de_tpl_CONTRIBUTING.rst
aedev/project_tpls/templates/de_otf_de_tpl_dev_requirements.txt
aedev/project_tpls/templates/de_otf_de_tpl_setup.py
aedev/project_tpls/templates/de_otf_pyproject.toml
aedev/project_tpls/templates/de_sfp_de_otf_de_tpl_.readthedocs.yaml
aedev/project_tpls/templates/de_tpl_README.md
aedev/project_tpls/templates/de_sfp_docs/de_otf_Makefile
aedev/project_tpls/templates/de_sfp_docs/de_otf_de_tpl_conf.py
aedev/project_tpls/templates/de_sfp_docs/de_otf_de_tpl_index.rst
aedev/project_tpls/templates/de_sfp_docs/de_otf_de_tpl_requirements.txt
aedev/project_tpls/templates/de_sfp_docs/features_and_examples.rst
aedev/project_tpls/templates/tests/de_otf_conftest.py
aedev/project_tpls/templates/tests/de_otf_de_tpl_requirements.txt
aedev/project_tpls/templates/tests/de_tpl_test_{portion_name or project_name}.py
aedev_project_tpls-0.3.75.dist-info/licenses/LICENSE.md
aedev_project_tpls-0.3.75.dist-info/METADATA
aedev_project_tpls-0.3.75.dist-info/WHEEL
aedev_project_tpls-0.3.75.dist-info/top_level.txt
aedev_project_tpls-0.3.75.dist-info/RECORD
